pulumi_provider_boilerplate/__init__.py
pulumi_provider_boilerplate/_utilities.py
pulumi_provider_boilerplate/provider.py
pulumi_provider_boilerplate/pulumi-plugin.json
pulumi_provider_boilerplate/py.typed
pulumi_provider_boilerplate/random.py
pulumi_provider_boilerplate/random_component.py
pulumi_provider_boilerplate/config/__init__.py
pulumi_provider_boilerplate/config/__init__.pyi
pulumi_provider_boilerplate/config/vars.py
pulumi_provider_boilerplate-0.0.172.dist-info/METADATA
pulumi_provider_boilerplate-0.0.172.dist-info/WHEEL
pulumi_provider_boilerplate-0.0.172.dist-info/top_level.txt
pulumi_provider_boilerplate-0.0.172.dist-info/RECORD
