Metadata-Version: 2.4
Name: pulumi_provider_boilerplate
Version: 0.0.172
Summary: An example built with pulumi-go-provider.
Project-URL: Homepage, https://www.pulumi.com
Requires-Python: >=3.9
Requires-Dist: parver>=0.2.1
Requires-Dist: pulumi<4.0.0,>=3.165.0
Requires-Dist: semver>=2.8.1
Requires-Dist: typing-extensions<5,>=4.11; python_version < "3.11"
